COPYING
README.rst
TODO.rst
setup.py
PyLIME.egg-info/PKG-INFO
PyLIME.egg-info/SOURCES.txt
PyLIME.egg-info/dependency_links.txt
PyLIME.egg-info/top_level.txt
devel/requirements.text
devel/template.py
doc/LIME_format.rst
doc/devel/TODO_release.rst
pylime/__init__.py
pylime/exceptions.py
pylime/globals.py
pylime/limefile.py
pylime/limeheader.py
pylime/limemsg.py
pylime/limereader.py
pylime/limerecord.py
pylime/limewriter.py
pylime/utils.py
pylime/version.py